evsetool/__init__.py
evsetool/__main__.py
evsetool/csms.py
evsetool/evse.py
evsetool/sniffer.py
evsetool/utils.py
evsetool/wifi_decryptor.py
evsetool-0.1.5.dist-info/METADATA
evsetool-0.1.5.dist-info/WHEEL
evsetool-0.1.5.dist-info/licenses/LICENSE.md
evsetool-0.1.5.dist-info/RECORD
