Metadata-Version: 2.4
Name: evsetool
Version: 0.1.5
Summary: EVSE Red Team Toolkit
Project-URL: Homepage, https://github.com/witchofthewires/evsetool.git
Project-URL: Issues, https://github.com/witchofthewires/evsetool.git/issues
Author-email: Danielle McGuire <dcm678@gmail.com>
License-File: LICENSE.md
Classifier: License :: OSI Approved :: MIT License
Classifier: Operating System :: OS Independent
Classifier: Programming Language :: Python :: 3
Requires-Python: >=3.8
Requires-Dist: asyncio
Requires-Dist: coverage
Requires-Dist: ocpp
Requires-Dist: pytest
Requires-Dist: pyyaml
Requires-Dist: scapy
Requires-Dist: websockets
